{
  "operatorType": "ESTELLA",
  "name": "Estella",
  "operatorRarity": 4,
  "operatorClassType": "GUARD",
  "elementType": "CRYO",
  "weaponType": "POLEARM",
  "mainAttributeType": "WILL",
  "secondaryAttributeType": "STRENGTH",
  "potentials": [
    {
      "level": 1,
      "name": "Habitual Delay",
      "effects": [
        {
          "potentialEffectType": "SKILL_PARAMETER",
          "skillParameterModifier": {
            "skillType": "ESTELLA_DISTORTION",
            "parameterKey": "has_potential1",
            "value": 1,
            "parameterModifyType": "UNIQUE_MULTIPLIER"
          }
        },
        {
          "potentialEffectType": "SKILL_PARAMETER",
          "skillParameterModifier": {
            "skillType": "ESTELLA_DISTORTION",
            "parameterKey": "rate_plus",
            "value": 3,
            "parameterModifyType": "UNIQUE_MULTIPLIER"
          }
        }
      ]
    },
    {
      "level": 2,
      "name": "Lowered Expectations",
      "effects": [
        {
          "potentialEffectType": "SKILL_COST",
          "skillCostModifier": {
            "skillType": "ESTELLA_TREMOLO",
            "parameterType": 1,
            "value": 0.9
          }
        }
      ]
    },
    {
      "level": 3,
      "name": "Delayed Work",
      "effects": [
        {
          "potentialEffectType": "SKILL_PARAMETER",
          "skillParameterModifier": {
            "skillType": "ESTELLA_ONOMATOPOEIA",
            "parameterKey": "distance",
            "value": 12,
            "parameterModifyType": "UNIQUE_MULTIPLIER"
          }
        },
        {
          "potentialEffectType": "SKILL_PARAMETER",
          "skillParameterModifier": {
            "skillType": "ESTELLA_ONOMATOPOEIA",
            "parameterKey": "dmg_up",
            "value": 0.4,
            "parameterModifyType": "UNIQUE_MULTIPLIER"
          }
        }
      ]
    },
    {
      "level": 4,
      "name": "Life Over Mission",
      "effects": [
        {
          "potentialEffectType": "STAT_MODIFIER",
          "statModifier": {
            "statType": "WILL",
            "value": 10
          }
        },
        {
          "potentialEffectType": "STAT_MODIFIER",
          "statModifier": {
            "statType": "STRENGTH",
            "value": 10
          }
        }
      ]
    },
    {
      "level": 5,
      "name": "Survival is a Win",
      "effects": [
        {
          "potentialEffectType": "BUFF_ATTACHMENT",
          "buffAttachment": {
            "statusType": "ESTELLA_POTENTIAL5_SURVIVAL_IS_A_WIN",
            "parameters": [
              {
                "key": "usp",
                "value": 5,
                "valueStr": ""
              }
            ]
          }
        }
      ]
    }
  ],
  "allLevels": [
    {
      "level": 1,
      "operatorPromotionStage": 0,
      "attributes": {
        "STRENGTH": 13.041237113402063,
        "AGILITY": 8.762886597938145,
        "INTELLECT": 14.123711340206187,
        "WILL": 15.000000000000002,
        "BASE_HP": 500,
        "BASE_ATTACK": 30,
        "BASE_DEFENSE": 0,
        "WEIGHT": 1,
        "CRITICAL_RATE": 0.05,
        "ATTACK_RANGE": 3
      }
    },
    {
      "level": 2,
      "operatorPromotionStage": 0,
      "attributes": {
        "STRENGTH": 14.070418682937094,
        "AGILITY": 9.764148958552495,
        "INTELLECT": 15.20660635388176,
        "WILL": 16.53408373658742,
        "BASE_HP": 556,
        "BASE_ATTACK": 33,
        "BASE_DEFENSE": 0,
        "WEIGHT": 1,
        "CRITICAL_RATE": 0.05,
        "ATTACK_RANGE": 3
      }
    },
    {
      "level": 3,
      "operatorPromotionStage": 0,
      "attributes": {
        "STRENGTH": 15.099600252472126,
        "AGILITY": 10.765411319166843,
        "INTELLECT": 16.289501367557335,
        "WILL": 18.06816747317484,
        "BASE_HP": 612,
        "BASE_ATTACK": 36,
        "BASE_DEFENSE": 0,
        "WEIGHT": 1,
        "CRITICAL_RATE": 0.05,
        "ATTACK_RANGE": 3
      }
    },
    {
      "level": 4,
      "operatorPromotionStage": 0,
      "attributes": {
        "STRENGTH": 16.128781822007156,
        "AGILITY": 11.766673679781192,
        "INTELLECT": 17.372396381232907,
        "WILL": 19.602251209762258,
        "BASE_HP": 668,
        "BASE_ATTACK": 39,
        "BASE_DEFENSE": 0,
        "WEIGHT": 1,
        "CRITICAL_RATE": 0.05,
        "ATTACK_RANGE": 3
      }
    },
    {
      "level": 5,
      "operatorPromotionStage": 0,
      "attributes": {
        "STRENGTH": 17.157963391542186,
        "AGILITY": 12.76793604039554,
        "INTELLECT": 18.455291394908482,
        "WILL": 21.136334946349677,
        "BASE_HP": 724,
        "BASE_ATTACK": 43,
        "BASE_DEFENSE": 0,
        "WEIGHT": 1,
        "CRITICAL_RATE": 0.05,
        "ATTACK_RANGE": 3
      }
    },
    {
      "level": 6,
      "operatorPromotionStage": 0,
      "attributes": {
        "STRENGTH": 18.187144961077216,
        "AGILITY": 13.76919840100989,
        "INTELLECT": 19.538186408584053,
        "WILL": 22.670418682937093,
        "BASE_HP": 781,
        "BASE_ATTACK": 46,
        "BASE_DEFENSE": 0,
        "WEIGHT": 1,
        "CRITICAL_RATE": 0.05,
        "ATTACK_RANGE": 3
      }
    },
    {
      "level": 7,
      "operatorPromotionStage": 0,
      "attributes": {
        "STRENGTH": 19.216326530612246,
        "AGILITY": 14.77046076162424,
        "INTELLECT": 20.62108142225963,
        "WILL": 24.204502419524513,
        "BASE_HP": 837,
        "BASE_ATTACK": 49,
        "BASE_DEFENSE": 0,
        "WEIGHT": 1,
        "CRITICAL_RATE": 0.05,
        "ATTACK_RANGE": 3
      }
    },
    {
      "level": 8,
      "operatorPromotionStage": 0,
      "attributes": {
        "STRENGTH": 20.245508100147276,
        "AGILITY": 15.771723122238587,
        "INTELLECT": 21.703976435935203,
        "WILL": 25.73858615611193,
        "BASE_HP": 893,
        "BASE_ATTACK": 52,
        "BASE_DEFENSE": 0,
        "WEIGHT": 1,
        "CRITICAL_RATE": 0.05,
        "ATTACK_RANGE": 3
      }
    },
    {
      "level": 9,
      "operatorPromotionStage": 0,
      "attributes": {
        "STRENGTH": 21.27468966968231,
        "AGILITY": 16.77298548285294,
        "INTELLECT": 22.786871449610775,
        "WILL": 27.272669892699348,
        "BASE_HP": 949,
        "BASE_ATTACK": 55,
        "BASE_DEFENSE": 0,
        "WEIGHT": 1,
        "CRITICAL_RATE": 0.05,
        "ATTACK_RANGE": 3
      }
    },
    {
      "level": 10,
      "operatorPromotionStage": 0,
      "attributes": {
        "STRENGTH": 22.303871239217337,
        "AGILITY": 17.774247843467286,
        "INTELLECT": 23.869766463286346,
        "WILL": 28.806753629286767,
        "BASE_HP": 1005,
        "BASE_ATTACK": 58,
        "BASE_DEFENSE": 0,
        "WEIGHT": 1,
        "CRITICAL_RATE": 0.05,
        "ATTACK_RANGE": 3
      }
    },
    {
      "level": 11,
      "operatorPromotionStage": 0,
      "attributes": {
        "STRENGTH": 23.33305280875237,
        "AGILITY": 18.775510204081634,
        "INTELLECT": 24.95266147696192,
        "WILL": 30.340837365874187,
        "BASE_HP": 1061,
        "BASE_ATTACK": 62,
        "BASE_DEFENSE": 0,
        "WEIGHT": 1,
        "CRITICAL_RATE": 0.05,
        "ATTACK_RANGE": 3
      }
    },
    {
      "level": 12,
      "operatorPromotionStage": 0,
      "attributes": {
        "STRENGTH": 24.3622343782874,
        "AGILITY": 19.77677256469598,
        "INTELLECT": 26.035556490637497,
        "WILL": 31.874921102461606,
        "BASE_HP": 1117,
        "BASE_ATTACK": 65,
        "BASE_DEFENSE": 0,
        "WEIGHT": 1,
        "CRITICAL_RATE": 0.05,
        "ATTACK_RANGE": 3
      }
    },
    {
      "level": 13,
      "operatorPromotionStage": 0,
      "attributes": {
        "STRENGTH": 25.39141594782243,
        "AGILITY": 20.778034925310333,
        "INTELLECT": 27.11845150431307,
        "WILL": 33.409004839049025,
        "BASE_HP": 1173,
        "BASE_ATTACK": 68,
        "BASE_DEFENSE": 0,
        "WEIGHT": 1,
        "CRITICAL_RATE": 0.05,
        "ATTACK_RANGE": 3
      }
    },
    {
      "level": 14,
      "operatorPromotionStage": 0,
      "attributes": {
        "STRENGTH": 26.42059751735746,
        "AGILITY": 21.77929728592468,
        "INTELLECT": 28.201346517988643,
        "WILL": 34.943088575636445,
        "BASE_HP": 1230,
        "BASE_ATTACK": 71,
        "BASE_DEFENSE": 0,
        "WEIGHT": 1,
        "CRITICAL_RATE": 0.05,
        "ATTACK_RANGE": 3
      }
    },
    {
      "level": 15,
      "operatorPromotionStage": 0,
      "attributes": {
        "STRENGTH": 27.44977908689249,
        "AGILITY": 22.780559646539032,
        "INTELLECT": 29.284241531664215,
        "WILL": 36.47717231222386,
        "BASE_HP": 1286,
        "BASE_ATTACK": 74,
        "BASE_DEFENSE": 0,
        "WEIGHT": 1,
        "CRITICAL_RATE": 0.05,
        "ATTACK_RANGE": 3
      }
    },
    {
      "level": 16,
      "operatorPromotionStage": 0,
      "attributes": {
        "STRENGTH": 28.478960656427525,
        "AGILITY": 23.78182200715338,
        "INTELLECT": 30.36713654533979,
        "WILL": 38.011256048811276,
        "BASE_HP": 1342,
        "BASE_ATTACK": 77,
        "BASE_DEFENSE": 0,
        "WEIGHT": 1,
        "CRITICAL_RATE": 0.05,
        "ATTACK_RANGE": 3
      }
    },
    {
      "level": 17,
      "operatorPromotionStage": 0,
      "attributes": {
        "STRENGTH": 29.50814222596255,
        "AGILITY": 24.783084367767728,
        "INTELLECT": 31.450031559015365,
        "WILL": 39.545339785398696,
        "BASE_HP": 1398,
        "BASE_ATTACK": 81,
        "BASE_DEFENSE": 0,
        "WEIGHT": 1,
        "CRITICAL_RATE": 0.05,
        "ATTACK_RANGE": 3
      }
    },
    {
      "level": 18,
      "operatorPromotionStage": 0,
      "attributes": {
        "STRENGTH": 30.537323795497585,
        "AGILITY": 25.784346728382076,
        "INTELLECT": 32.53292657269094,
        "WILL": 41.079423521986115,
        "BASE_HP": 1454,
        "BASE_ATTACK": 84,
        "BASE_DEFENSE": 0,
        "WEIGHT": 1,
        "CRITICAL_RATE": 0.05,
        "ATTACK_RANGE": 3
      }
    },
    {
      "level": 19,
      "operatorPromotionStage": 0,
      "attributes": {
        "STRENGTH": 31.56650536503261,
        "AGILITY": 26.785609088996427,
        "INTELLECT": 33.61582158636651,
        "WILL": 42.613507258573534,
        "BASE_HP": 1510,
        "BASE_ATTACK": 87,
        "BASE_DEFENSE": 0,
        "WEIGHT": 1,
        "CRITICAL_RATE": 0.05,
        "ATTACK_RANGE": 3
      }
    },
    {
      "level": 20,
      "operatorPromotionStage": 0,
      "attributes": {
        "STRENGTH": 32.595686934567645,
        "AGILITY": 27.786871449610775,
        "INTELLECT": 34.69871660004208,
        "WILL": 44.147590995160954,
        "BASE_HP": 1566,
        "BASE_ATTACK": 90,
        "BASE_DEFENSE": 0,
        "WEIGHT": 1,
        "CRITICAL_RATE": 0.05,
        "ATTACK_RANGE": 3
      }
    },
    {
      "level": 20,
      "operatorPromotionStage": 1,
      "attributes": {
        "STRENGTH": 32.595686934567645,
        "AGILITY": 27.786871449610775,
        "INTELLECT": 34.69871660004208,
        "WILL": 44.147590995160954,
        "BASE_HP": 1566,
        "BASE_ATTACK": 90,
        "BASE_DEFENSE": 0,
        "WEIGHT": 1,
        "CRITICAL_RATE": 0.05,
        "ATTACK_RANGE": 3
      }
    },
    {
      "level": 21,
      "operatorPromotionStage": 1,
      "attributes": {
        "STRENGTH": 33.62486850410267,
        "AGILITY": 28.788133810225123,
        "INTELLECT": 35.78161161371766,
        "WILL": 45.68167473174837,
        "BASE_HP": 1622,
        "BASE_ATTACK": 93,
        "BASE_DEFENSE": 0,
        "WEIGHT": 1,
        "CRITICAL_RATE": 0.05,
        "ATTACK_RANGE": 3
      }
    },
    {
      "level": 22,
      "operatorPromotionStage": 1,
      "attributes": {
        "STRENGTH": 34.654050073637706,
        "AGILITY": 29.789396170839474,
        "INTELLECT": 36.86450662739323,
        "WILL": 47.215758468335785,
        "BASE_HP": 1679,
        "BASE_ATTACK": 96,
        "BASE_DEFENSE": 0,
        "WEIGHT": 1,
        "CRITICAL_RATE": 0.05,
        "ATTACK_RANGE": 3
      }
    },
    {
      "level": 23,
      "operatorPromotionStage": 1,
      "attributes": {
        "STRENGTH": 35.68323164317274,
        "AGILITY": 30.790658531453822,
        "INTELLECT": 37.9474016410688,
        "WILL": 48.749842204923205,
        "BASE_HP": 1735,
        "BASE_ATTACK": 100,
        "BASE_DEFENSE": 0,
        "WEIGHT": 1,
        "CRITICAL_RATE": 0.05,
        "ATTACK_RANGE": 3
      }
    },
    {
      "level": 24,
      "operatorPromotionStage": 1,
      "attributes": {
        "STRENGTH": 36.712413212707766,
        "AGILITY": 31.79192089206817,
        "INTELLECT": 39.030296654744376,
        "WILL": 50.283925941510624,
        "BASE_HP": 1791,
        "BASE_ATTACK": 103,
        "BASE_DEFENSE": 0,
        "WEIGHT": 1,
        "CRITICAL_RATE": 0.05,
        "ATTACK_RANGE": 3
      }
    },
    {
      "level": 25,
      "operatorPromotionStage": 1,
      "attributes": {
        "STRENGTH": 37.7415947822428,
        "AGILITY": 32.793183252682525,
        "INTELLECT": 40.11319166841995,
        "WILL": 51.81800967809804,
        "BASE_HP": 1847,
        "BASE_ATTACK": 106,
        "BASE_DEFENSE": 0,
        "WEIGHT": 1,
        "CRITICAL_RATE": 0.05,
        "ATTACK_RANGE": 3
      }
    },
    {
      "level": 26,
      "operatorPromotionStage": 1,
      "attributes": {
        "STRENGTH": 38.770776351777826,
        "AGILITY": 33.79444561329687,
        "INTELLECT": 41.196086682095526,
        "WILL": 53.35209341468546,
        "BASE_HP": 1903,
        "BASE_ATTACK": 109,
        "BASE_DEFENSE": 0,
        "WEIGHT": 1,
        "CRITICAL_RATE": 0.05,
        "ATTACK_RANGE": 3
      }
    },
    {
      "level": 27,
      "operatorPromotionStage": 1,
      "attributes": {
        "STRENGTH": 39.79995792131286,
        "AGILITY": 34.79570797391122,
        "INTELLECT": 42.2789816957711,
        "WILL": 54.88617715127288,
        "BASE_HP": 1959,
        "BASE_ATTACK": 112,
        "BASE_DEFENSE": 0,
        "WEIGHT": 1,
        "CRITICAL_RATE": 0.05,
        "ATTACK_RANGE": 3
      }
    },
    {
      "level": 28,
      "operatorPromotionStage": 1,
      "attributes": {
        "STRENGTH": 40.829139490847886,
        "AGILITY": 35.79697033452557,
        "INTELLECT": 43.36187670944667,
        "WILL": 56.4202608878603,
        "BASE_HP": 2015,
        "BASE_ATTACK": 115,
        "BASE_DEFENSE": 0,
        "WEIGHT": 1,
        "CRITICAL_RATE": 0.05,
        "ATTACK_RANGE": 3
      }
    },
    {
      "level": 29,
      "operatorPromotionStage": 1,
      "attributes": {
        "STRENGTH": 41.85832106038292,
        "AGILITY": 36.798232695139916,
        "INTELLECT": 44.444771723122244,
        "WILL": 57.954344624447714,
        "BASE_HP": 2071,
        "BASE_ATTACK": 119,
        "BASE_DEFENSE": 0,
        "WEIGHT": 1,
        "CRITICAL_RATE": 0.05,
        "ATTACK_RANGE": 3
      }
    },
    {
      "level": 30,
      "operatorPromotionStage": 1,
      "attributes": {
        "STRENGTH": 42.887502629917954,
        "AGILITY": 37.799495055754264,
        "INTELLECT": 45.52766673679782,
        "WILL": 59.48842836103513,
        "BASE_HP": 2128,
        "BASE_ATTACK": 122,
        "BASE_DEFENSE": 0,
        "WEIGHT": 1,
        "CRITICAL_RATE": 0.05,
        "ATTACK_RANGE": 3
      }
    },
    {
      "level": 31,
      "operatorPromotionStage": 1,
      "attributes": {
        "STRENGTH": 43.91668419945298,
        "AGILITY": 38.80075741636861,
        "INTELLECT": 46.61056175047339,
        "WILL": 61.02251209762255,
        "BASE_HP": 2184,
        "BASE_ATTACK": 125,
        "BASE_DEFENSE": 0,
        "WEIGHT": 1,
        "CRITICAL_RATE": 0.05,
        "ATTACK_RANGE": 3
      }
    },
    {
      "level": 32,
      "operatorPromotionStage": 1,
      "attributes": {
        "STRENGTH": 44.945865768988014,
        "AGILITY": 39.80201977698296,
        "INTELLECT": 47.69345676414896,
        "WILL": 62.55659583420997,
        "BASE_HP": 2240,
        "BASE_ATTACK": 128,
        "BASE_DEFENSE": 0,
        "WEIGHT": 1,
        "CRITICAL_RATE": 0.05,
        "ATTACK_RANGE": 3
      }
    },
    {
      "level": 33,
      "operatorPromotionStage": 1,
      "attributes": {
        "STRENGTH": 45.97504733852304,
        "AGILITY": 40.80328213759731,
        "INTELLECT": 48.77635177782454,
        "WILL": 64.09067957079739,
        "BASE_HP": 2296,
        "BASE_ATTACK": 131,
        "BASE_DEFENSE": 0,
        "WEIGHT": 1,
        "CRITICAL_RATE": 0.05,
        "ATTACK_RANGE": 3
      }
    },
    {
      "level": 34,
      "operatorPromotionStage": 1,
      "attributes": {
        "STRENGTH": 47.004228908058074,
        "AGILITY": 41.804544498211655,
        "INTELLECT": 49.85924679150011,
        "WILL": 65.62476330738481,
        "BASE_HP": 2352,
        "BASE_ATTACK": 134,
        "BASE_DEFENSE": 0,
        "WEIGHT": 1,
        "CRITICAL_RATE": 0.05,
        "ATTACK_RANGE": 3
      }
    },
    {
      "level": 35,
      "operatorPromotionStage": 1,
      "attributes": {
        "STRENGTH": 48.0334104775931,
        "AGILITY": 42.805806858826,
        "INTELLECT": 50.94214180517569,
        "WILL": 67.15884704397223,
        "BASE_HP": 2408,
        "BASE_ATTACK": 138,
        "BASE_DEFENSE": 0,
        "WEIGHT": 1,
        "CRITICAL_RATE": 0.05,
        "ATTACK_RANGE": 3
      }
    },
    {
      "level": 36,
      "operatorPromotionStage": 1,
      "attributes": {
        "STRENGTH": 49.062592047128135,
        "AGILITY": 43.80706921944035,
        "INTELLECT": 52.025036818851255,
        "WILL": 68.69293078055965,
        "BASE_HP": 2464,
        "BASE_ATTACK": 141,
        "BASE_DEFENSE": 0,
        "WEIGHT": 1,
        "CRITICAL_RATE": 0.05,
        "ATTACK_RANGE": 3
      }
    },
    {
      "level": 37,
      "operatorPromotionStage": 1,
      "attributes": {
        "STRENGTH": 50.09177361666316,
        "AGILITY": 44.80833158005471,
        "INTELLECT": 53.10793183252683,
        "WILL": 70.22701451714707,
        "BASE_HP": 2520,
        "BASE_ATTACK": 144,
        "BASE_DEFENSE": 0,
        "WEIGHT": 1,
        "CRITICAL_RATE": 0.05,
        "ATTACK_RANGE": 3
      }
    },
    {
      "level": 38,
      "operatorPromotionStage": 1,
      "attributes": {
        "STRENGTH": 51.120955186198195,
        "AGILITY": 45.80959394066906,
        "INTELLECT": 54.190826846202405,
        "WILL": 71.76109825373449,
        "BASE_HP": 2577,
        "BASE_ATTACK": 147,
        "BASE_DEFENSE": 0,
        "WEIGHT": 1,
        "CRITICAL_RATE": 0.05,
        "ATTACK_RANGE": 3
      }
    },
    {
      "level": 39,
      "operatorPromotionStage": 1,
      "attributes": {
        "STRENGTH": 52.15013675573322,
        "AGILITY": 46.81085630128341,
        "INTELLECT": 55.27372185987798,
        "WILL": 73.29518199032191,
        "BASE_HP": 2633,
        "BASE_ATTACK": 150,
        "BASE_DEFENSE": 0,
        "WEIGHT": 1,
        "CRITICAL_RATE": 0.05,
        "ATTACK_RANGE": 3
      }
    },
    {
      "level": 40,
      "operatorPromotionStage": 1,
      "attributes": {
        "STRENGTH": 53.179318325268255,
        "AGILITY": 47.812118661897756,
        "INTELLECT": 56.35661687355355,
        "WILL": 74.82926572690933,
        "BASE_HP": 2689,
        "BASE_ATTACK": 153,
        "BASE_DEFENSE": 0,
        "WEIGHT": 1,
        "CRITICAL_RATE": 0.05,
        "ATTACK_RANGE": 3
      }
    },
    {
      "level": 40,
      "operatorPromotionStage": 2,
      "attributes": {
        "STRENGTH": 53.179318325268255,
        "AGILITY": 47.812118661897756,
        "INTELLECT": 56.35661687355355,
        "WILL": 74.82926572690933,
        "BASE_HP": 2689,
        "BASE_ATTACK": 153,
        "BASE_DEFENSE": 0,
        "WEIGHT": 1,
        "CRITICAL_RATE": 0.05,
        "ATTACK_RANGE": 3
      }
    },
    {
      "level": 41,
      "operatorPromotionStage": 2,
      "attributes": {
        "STRENGTH": 54.20849989480328,
        "AGILITY": 48.813381022512104,
        "INTELLECT": 57.43951188722912,
        "WILL": 76.36334946349675,
        "BASE_HP": 2745,
        "BASE_ATTACK": 157,
        "BASE_DEFENSE": 0,
        "WEIGHT": 1,
        "CRITICAL_RATE": 0.05,
        "ATTACK_RANGE": 3
      }
    },
    {
      "level": 42,
      "operatorPromotionStage": 2,
      "attributes": {
        "STRENGTH": 55.237681464338316,
        "AGILITY": 49.81464338312645,
        "INTELLECT": 58.5224069009047,
        "WILL": 77.89743320008417,
        "BASE_HP": 2801,
        "BASE_ATTACK": 160,
        "BASE_DEFENSE": 0,
        "WEIGHT": 1,
        "CRITICAL_RATE": 0.05,
        "ATTACK_RANGE": 3
      }
    },
    {
      "level": 43,
      "operatorPromotionStage": 2,
      "attributes": {
        "STRENGTH": 56.26686303387335,
        "AGILITY": 50.8159057437408,
        "INTELLECT": 59.605301914580274,
        "WILL": 79.43151693667157,
        "BASE_HP": 2857,
        "BASE_ATTACK": 163,
        "BASE_DEFENSE": 0,
        "WEIGHT": 1,
        "CRITICAL_RATE": 0.05,
        "ATTACK_RANGE": 3
      }
    },
    {
      "level": 44,
      "operatorPromotionStage": 2,
      "attributes": {
        "STRENGTH": 57.296044603408376,
        "AGILITY": 51.81716810435515,
        "INTELLECT": 60.68819692825585,
        "WILL": 80.96560067325899,
        "BASE_HP": 2913,
        "BASE_ATTACK": 166,
        "BASE_DEFENSE": 0,
        "WEIGHT": 1,
        "CRITICAL_RATE": 0.05,
        "ATTACK_RANGE": 3
      }
    },
    {
      "level": 45,
      "operatorPromotionStage": 2,
      "attributes": {
        "STRENGTH": 58.32522617294341,
        "AGILITY": 52.818430464969495,
        "INTELLECT": 61.77109194193142,
        "WILL": 82.49968440984641,
        "BASE_HP": 2969,
        "BASE_ATTACK": 169,
        "BASE_DEFENSE": 0,
        "WEIGHT": 1,
        "CRITICAL_RATE": 0.05,
        "ATTACK_RANGE": 3
      }
    },
    {
      "level": 46,
      "operatorPromotionStage": 2,
      "attributes": {
        "STRENGTH": 59.354407742478436,
        "AGILITY": 53.81969282558384,
        "INTELLECT": 62.85398695560699,
        "WILL": 84.03376814643383,
        "BASE_HP": 3026,
        "BASE_ATTACK": 172,
        "BASE_DEFENSE": 0,
        "WEIGHT": 1,
        "CRITICAL_RATE": 0.05,
        "ATTACK_RANGE": 3
      }
    },
    {
      "level": 47,
      "operatorPromotionStage": 2,
      "attributes": {
        "STRENGTH": 60.38358931201347,
        "AGILITY": 54.82095518619819,
        "INTELLECT": 63.93688196928257,
        "WILL": 85.56785188302125,
        "BASE_HP": 3082,
        "BASE_ATTACK": 176,
        "BASE_DEFENSE": 0,
        "WEIGHT": 1,
        "CRITICAL_RATE": 0.05,
        "ATTACK_RANGE": 3
      }
    },
    {
      "level": 48,
      "operatorPromotionStage": 2,
      "attributes": {
        "STRENGTH": 61.4127708815485,
        "AGILITY": 55.82221754681254,
        "INTELLECT": 65.01977698295815,
        "WILL": 87.10193561960867,
        "BASE_HP": 3138,
        "BASE_ATTACK": 179,
        "BASE_DEFENSE": 0,
        "WEIGHT": 1,
        "CRITICAL_RATE": 0.05,
        "ATTACK_RANGE": 3
      }
    },
    {
      "level": 49,
      "operatorPromotionStage": 2,
      "attributes": {
        "STRENGTH": 62.44195245108353,
        "AGILITY": 56.8234799074269,
        "INTELLECT": 66.10267199663372,
        "WILL": 88.63601935619609,
        "BASE_HP": 3194,
        "BASE_ATTACK": 182,
        "BASE_DEFENSE": 0,
        "WEIGHT": 1,
        "CRITICAL_RATE": 0.05,
        "ATTACK_RANGE": 3
      }
    },
    {
      "level": 50,
      "operatorPromotionStage": 2,
      "attributes": {
        "STRENGTH": 63.471134020618564,
        "AGILITY": 57.82474226804125,
        "INTELLECT": 67.18556701030928,
        "WILL": 90.1701030927835,
        "BASE_HP": 3250,
        "BASE_ATTACK": 185,
        "BASE_DEFENSE": 0,
        "WEIGHT": 1,
        "CRITICAL_RATE": 0.05,
        "ATTACK_RANGE": 3
      }
    },
    {
      "level": 51,
      "operatorPromotionStage": 2,
      "attributes": {
        "STRENGTH": 64.50031559015359,
        "AGILITY": 58.826004628655596,
        "INTELLECT": 68.26846202398487,
        "WILL": 91.70418682937093,
        "BASE_HP": 3306,
        "BASE_ATTACK": 188,
        "BASE_DEFENSE": 0,
        "WEIGHT": 1,
        "CRITICAL_RATE": 0.05,
        "ATTACK_RANGE": 3
      }
    },
    {
      "level": 52,
      "operatorPromotionStage": 2,
      "attributes": {
        "STRENGTH": 65.52949715968863,
        "AGILITY": 59.827266989269944,
        "INTELLECT": 69.35135703766043,
        "WILL": 93.23827056595835,
        "BASE_HP": 3362,
        "BASE_ATTACK": 191,
        "BASE_DEFENSE": 0,
        "WEIGHT": 1,
        "CRITICAL_RATE": 0.05,
        "ATTACK_RANGE": 3
      }
    },
    {
      "level": 53,
      "operatorPromotionStage": 2,
      "attributes": {
        "STRENGTH": 66.55867872922366,
        "AGILITY": 60.82852934988429,
        "INTELLECT": 70.43425205133602,
        "WILL": 94.77235430254576,
        "BASE_HP": 3418,
        "BASE_ATTACK": 195,
        "BASE_DEFENSE": 0,
        "WEIGHT": 1,
        "CRITICAL_RATE": 0.05,
        "ATTACK_RANGE": 3
      }
    },
    {
      "level": 54,
      "operatorPromotionStage": 2,
      "attributes": {
        "STRENGTH": 67.58786029875868,
        "AGILITY": 61.82979171049864,
        "INTELLECT": 71.51714706501159,
        "WILL": 96.30643803913318,
        "BASE_HP": 3474,
        "BASE_ATTACK": 198,
        "BASE_DEFENSE": 0,
        "WEIGHT": 1,
        "CRITICAL_RATE": 0.05,
        "ATTACK_RANGE": 3
      }
    },
    {
      "level": 55,
      "operatorPromotionStage": 2,
      "attributes": {
        "STRENGTH": 68.61704186829371,
        "AGILITY": 62.83105407111299,
        "INTELLECT": 72.60004207868715,
        "WILL": 97.8405217757206,
        "BASE_HP": 3531,
        "BASE_ATTACK": 201,
        "BASE_DEFENSE": 0,
        "WEIGHT": 1,
        "CRITICAL_RATE": 0.05,
        "ATTACK_RANGE": 3
      }
    },
    {
      "level": 56,
      "operatorPromotionStage": 2,
      "attributes": {
        "STRENGTH": 69.64622343782875,
        "AGILITY": 63.832316431727335,
        "INTELLECT": 73.68293709236274,
        "WILL": 99.37460551230802,
        "BASE_HP": 3587,
        "BASE_ATTACK": 204,
        "BASE_DEFENSE": 0,
        "WEIGHT": 1,
        "CRITICAL_RATE": 0.05,
        "ATTACK_RANGE": 3
      }
    },
    {
      "level": 57,
      "operatorPromotionStage": 2,
      "attributes": {
        "STRENGTH": 70.67540500736378,
        "AGILITY": 64.83357879234168,
        "INTELLECT": 74.7658321060383,
        "WILL": 100.90868924889543,
        "BASE_HP": 3643,
        "BASE_ATTACK": 207,
        "BASE_DEFENSE": 0,
        "WEIGHT": 1,
        "CRITICAL_RATE": 0.05,
        "ATTACK_RANGE": 3
      }
    },
    {
      "level": 58,
      "operatorPromotionStage": 2,
      "attributes": {
        "STRENGTH": 71.7045865768988,
        "AGILITY": 65.83484115295603,
        "INTELLECT": 75.84872711971389,
        "WILL": 102.44277298548285,
        "BASE_HP": 3699,
        "BASE_ATTACK": 210,
        "BASE_DEFENSE": 0,
        "WEIGHT": 1,
        "CRITICAL_RATE": 0.05,
        "ATTACK_RANGE": 3
      }
    },
    {
      "level": 59,
      "operatorPromotionStage": 2,
      "attributes": {
        "STRENGTH": 72.73376814643385,
        "AGILITY": 66.83610351357038,
        "INTELLECT": 76.93162213338945,
        "WILL": 103.97685672207027,
        "BASE_HP": 3755,
        "BASE_ATTACK": 214,
        "BASE_DEFENSE": 0,
        "WEIGHT": 1,
        "CRITICAL_RATE": 0.05,
        "ATTACK_RANGE": 3
      }
    },
    {
      "level": 60,
      "operatorPromotionStage": 2,
      "attributes": {
        "STRENGTH": 73.76294971596887,
        "AGILITY": 67.83736587418473,
        "INTELLECT": 78.01451714706502,
        "WILL": 105.51094045865769,
        "BASE_HP": 3811,
        "BASE_ATTACK": 217,
        "BASE_DEFENSE": 0,
        "WEIGHT": 1,
        "CRITICAL_RATE": 0.05,
        "ATTACK_RANGE": 3
      }
    },
    {
      "level": 60,
      "operatorPromotionStage": 3,
      "attributes": {
        "STRENGTH": 73.76294971596887,
        "AGILITY": 67.83736587418473,
        "INTELLECT": 78.01451714706502,
        "WILL": 105.51094045865769,
        "BASE_HP": 3811,
        "BASE_ATTACK": 217,
        "BASE_DEFENSE": 0,
        "WEIGHT": 1,
        "CRITICAL_RATE": 0.05,
        "ATTACK_RANGE": 3
      }
    },
    {
      "level": 61,
      "operatorPromotionStage": 3,
      "attributes": {
        "STRENGTH": 74.7921312855039,
        "AGILITY": 68.83862823479907,
        "INTELLECT": 79.09741216074059,
        "WILL": 107.0450241952451,
        "BASE_HP": 3867,
        "BASE_ATTACK": 220,
        "BASE_DEFENSE": 0,
        "WEIGHT": 1,
        "CRITICAL_RATE": 0.05,
        "ATTACK_RANGE": 3
      }
    },
    {
      "level": 62,
      "operatorPromotionStage": 3,
      "attributes": {
        "STRENGTH": 75.82131285503893,
        "AGILITY": 69.83989059541344,
        "INTELLECT": 80.18030717441617,
        "WILL": 108.57910793183252,
        "BASE_HP": 3923,
        "BASE_ATTACK": 223,
        "BASE_DEFENSE": 0,
        "WEIGHT": 1,
        "CRITICAL_RATE": 0.05,
        "ATTACK_RANGE": 3
      }
    },
    {
      "level": 63,
      "operatorPromotionStage": 3,
      "attributes": {
        "STRENGTH": 76.85049442457397,
        "AGILITY": 70.84115295602778,
        "INTELLECT": 81.26320218809174,
        "WILL": 110.11319166841994,
        "BASE_HP": 3980,
        "BASE_ATTACK": 226,
        "BASE_DEFENSE": 0,
        "WEIGHT": 1,
        "CRITICAL_RATE": 0.05,
        "ATTACK_RANGE": 3
      }
    },
    {
      "level": 64,
      "operatorPromotionStage": 3,
      "attributes": {
        "STRENGTH": 77.879675994109,
        "AGILITY": 71.84241531664213,
        "INTELLECT": 82.34609720176732,
        "WILL": 111.64727540500736,
        "BASE_HP": 4036,
        "BASE_ATTACK": 229,
        "BASE_DEFENSE": 0,
        "WEIGHT": 1,
        "CRITICAL_RATE": 0.05,
        "ATTACK_RANGE": 3
      }
    },
    {
      "level": 65,
      "operatorPromotionStage": 3,
      "attributes": {
        "STRENGTH": 78.90885756364402,
        "AGILITY": 72.84367767725648,
        "INTELLECT": 83.42899221544289,
        "WILL": 113.18135914159478,
        "BASE_HP": 4092,
        "BASE_ATTACK": 233,
        "BASE_DEFENSE": 0,
        "WEIGHT": 1,
        "CRITICAL_RATE": 0.05,
        "ATTACK_RANGE": 3
      }
    },
    {
      "level": 66,
      "operatorPromotionStage": 3,
      "attributes": {
        "STRENGTH": 79.93803913317905,
        "AGILITY": 73.84494003787083,
        "INTELLECT": 84.51188722911846,
        "WILL": 114.7154428781822,
        "BASE_HP": 4148,
        "BASE_ATTACK": 236,
        "BASE_DEFENSE": 0,
        "WEIGHT": 1,
        "CRITICAL_RATE": 0.05,
        "ATTACK_RANGE": 3
      }
    },
    {
      "level": 67,
      "operatorPromotionStage": 3,
      "attributes": {
        "STRENGTH": 80.96722070271409,
        "AGILITY": 74.84620239848518,
        "INTELLECT": 85.59478224279404,
        "WILL": 116.24952661476962,
        "BASE_HP": 4204,
        "BASE_ATTACK": 239,
        "BASE_DEFENSE": 0,
        "WEIGHT": 1,
        "CRITICAL_RATE": 0.05,
        "ATTACK_RANGE": 3
      }
    },
    {
      "level": 68,
      "operatorPromotionStage": 3,
      "attributes": {
        "STRENGTH": 81.99640227224911,
        "AGILITY": 75.84746475909952,
        "INTELLECT": 86.67767725646961,
        "WILL": 117.78361035135704,
        "BASE_HP": 4260,
        "BASE_ATTACK": 242,
        "BASE_DEFENSE": 0,
        "WEIGHT": 1,
        "CRITICAL_RATE": 0.05,
        "ATTACK_RANGE": 3
      }
    },
    {
      "level": 69,
      "operatorPromotionStage": 3,
      "attributes": {
        "STRENGTH": 83.02558384178414,
        "AGILITY": 76.84872711971387,
        "INTELLECT": 87.76057227014519,
        "WILL": 119.31769408794446,
        "BASE_HP": 4316,
        "BASE_ATTACK": 245,
        "BASE_DEFENSE": 0,
        "WEIGHT": 1,
        "CRITICAL_RATE": 0.05,
        "ATTACK_RANGE": 3
      }
    },
    {
      "level": 70,
      "operatorPromotionStage": 3,
      "attributes": {
        "STRENGTH": 84.05476541131917,
        "AGILITY": 77.84998948032822,
        "INTELLECT": 88.84346728382076,
        "WILL": 120.85177782453188,
        "BASE_HP": 4372,
        "BASE_ATTACK": 248,
        "BASE_DEFENSE": 0,
        "WEIGHT": 1,
        "CRITICAL_RATE": 0.05,
        "ATTACK_RANGE": 3
      }
    },
    {
      "level": 71,
      "operatorPromotionStage": 3,
      "attributes": {
        "STRENGTH": 85.08394698085421,
        "AGILITY": 78.85125184094257,
        "INTELLECT": 89.92636229749633,
        "WILL": 122.3858615611193,
        "BASE_HP": 4429,
        "BASE_ATTACK": 252,
        "BASE_DEFENSE": 0,
        "WEIGHT": 1,
        "CRITICAL_RATE": 0.05,
        "ATTACK_RANGE": 3
      }
    },
    {
      "level": 72,
      "operatorPromotionStage": 3,
      "attributes": {
        "STRENGTH": 86.11312855038923,
        "AGILITY": 79.85251420155693,
        "INTELLECT": 91.00925731117191,
        "WILL": 123.91994529770672,
        "BASE_HP": 4485,
        "BASE_ATTACK": 255,
        "BASE_DEFENSE": 0,
        "WEIGHT": 1,
        "CRITICAL_RATE": 0.05,
        "ATTACK_RANGE": 3
      }
    },
    {
      "level": 73,
      "operatorPromotionStage": 3,
      "attributes": {
        "STRENGTH": 87.14231011992426,
        "AGILITY": 80.85377656217128,
        "INTELLECT": 92.09215232484748,
        "WILL": 125.45402903429414,
        "BASE_HP": 4541,
        "BASE_ATTACK": 258,
        "BASE_DEFENSE": 0,
        "WEIGHT": 1,
        "CRITICAL_RATE": 0.05,
        "ATTACK_RANGE": 3
      }
    },
    {
      "level": 74,
      "operatorPromotionStage": 3,
      "attributes": {
        "STRENGTH": 88.1714916894593,
        "AGILITY": 81.85503892278562,
        "INTELLECT": 93.17504733852306,
        "WILL": 126.98811277088154,
        "BASE_HP": 4597,
        "BASE_ATTACK": 261,
        "BASE_DEFENSE": 0,
        "WEIGHT": 1,
        "CRITICAL_RATE": 0.05,
        "ATTACK_RANGE": 3
      }
    },
    {
      "level": 75,
      "operatorPromotionStage": 3,
      "attributes": {
        "STRENGTH": 89.20067325899433,
        "AGILITY": 82.85630128339997,
        "INTELLECT": 94.25794235219863,
        "WILL": 128.52219650746898,
        "BASE_HP": 4653,
        "BASE_ATTACK": 264,
        "BASE_DEFENSE": 0,
        "WEIGHT": 1,
        "CRITICAL_RATE": 0.05,
        "ATTACK_RANGE": 3
      }
    },
    {
      "level": 76,
      "operatorPromotionStage": 3,
      "attributes": {
        "STRENGTH": 90.22985482852935,
        "AGILITY": 83.85756364401432,
        "INTELLECT": 95.3408373658742,
        "WILL": 130.05628024405638,
        "BASE_HP": 4709,
        "BASE_ATTACK": 267,
        "BASE_DEFENSE": 0,
        "WEIGHT": 1,
        "CRITICAL_RATE": 0.05,
        "ATTACK_RANGE": 3
      }
    },
    {
      "level": 77,
      "operatorPromotionStage": 3,
      "attributes": {
        "STRENGTH": 91.25903639806438,
        "AGILITY": 84.85882600462867,
        "INTELLECT": 96.42373237954978,
        "WILL": 131.59036398064382,
        "BASE_HP": 4765,
        "BASE_ATTACK": 271,
        "BASE_DEFENSE": 0,
        "WEIGHT": 1,
        "CRITICAL_RATE": 0.05,
        "ATTACK_RANGE": 3
      }
    },
    {
      "level": 78,
      "operatorPromotionStage": 3,
      "attributes": {
        "STRENGTH": 92.28821796759942,
        "AGILITY": 85.86008836524302,
        "INTELLECT": 97.50662739322534,
        "WILL": 133.12444771723122,
        "BASE_HP": 4821,
        "BASE_ATTACK": 274,
        "BASE_DEFENSE": 0,
        "WEIGHT": 1,
        "CRITICAL_RATE": 0.05,
        "ATTACK_RANGE": 3
      }
    },
    {
      "level": 79,
      "operatorPromotionStage": 3,
      "attributes": {
        "STRENGTH": 93.31739953713445,
        "AGILITY": 86.86135072585736,
        "INTELLECT": 98.58952240690091,
        "WILL": 134.65853145381865,
        "BASE_HP": 4878,
        "BASE_ATTACK": 277,
        "BASE_DEFENSE": 0,
        "WEIGHT": 1,
        "CRITICAL_RATE": 0.05,
        "ATTACK_RANGE": 3
      }
    },
    {
      "level": 80,
      "operatorPromotionStage": 3,
      "attributes": {
        "STRENGTH": 94.34658110666948,
        "AGILITY": 87.86261308647171,
        "INTELLECT": 99.6724174205765,
        "WILL": 136.19261519040606,
        "BASE_HP": 4934,
        "BASE_ATTACK": 280,
        "BASE_DEFENSE": 0,
        "WEIGHT": 1,
        "CRITICAL_RATE": 0.05,
        "ATTACK_RANGE": 3
      }
    },
    {
      "level": 80,
      "operatorPromotionStage": 4,
      "attributes": {
        "STRENGTH": 94.34658110666948,
        "AGILITY": 87.86261308647171,
        "INTELLECT": 99.6724174205765,
        "WILL": 136.19261519040606,
        "BASE_HP": 4934,
        "BASE_ATTACK": 280,
        "BASE_DEFENSE": 0,
        "WEIGHT": 1,
        "CRITICAL_RATE": 0.05,
        "ATTACK_RANGE": 3
      }
    },
    {
      "level": 81,
      "operatorPromotionStage": 4,
      "attributes": {
        "STRENGTH": 95.3757626762045,
        "AGILITY": 88.86387544708606,
        "INTELLECT": 100.75531243425206,
        "WILL": 137.7266989269935,
        "BASE_HP": 4990,
        "BASE_ATTACK": 283,
        "BASE_DEFENSE": 0,
        "WEIGHT": 1,
        "CRITICAL_RATE": 0.05,
        "ATTACK_RANGE": 3
      }
    },
    {
      "level": 82,
      "operatorPromotionStage": 4,
      "attributes": {
        "STRENGTH": 96.40494424573954,
        "AGILITY": 89.8651378077004,
        "INTELLECT": 101.83820744792764,
        "WILL": 139.2607826635809,
        "BASE_HP": 5046,
        "BASE_ATTACK": 286,
        "BASE_DEFENSE": 0,
        "WEIGHT": 1,
        "CRITICAL_RATE": 0.05,
        "ATTACK_RANGE": 3
      }
    },
    {
      "level": 83,
      "operatorPromotionStage": 4,
      "attributes": {
        "STRENGTH": 97.43412581527457,
        "AGILITY": 90.86640016831475,
        "INTELLECT": 102.92110246160321,
        "WILL": 140.79486640016833,
        "BASE_HP": 5102,
        "BASE_ATTACK": 290,
        "BASE_DEFENSE": 0,
        "WEIGHT": 1,
        "CRITICAL_RATE": 0.05,
        "ATTACK_RANGE": 3
      }
    },
    {
      "level": 84,
      "operatorPromotionStage": 4,
      "attributes": {
        "STRENGTH": 98.4633073848096,
        "AGILITY": 91.8676625289291,
        "INTELLECT": 104.00399747527878,
        "WILL": 142.32895013675574,
        "BASE_HP": 5158,
        "BASE_ATTACK": 293,
        "BASE_DEFENSE": 0,
        "WEIGHT": 1,
        "CRITICAL_RATE": 0.05,
        "ATTACK_RANGE": 3
      }
    },
    {
      "level": 85,
      "operatorPromotionStage": 4,
      "attributes": {
        "STRENGTH": 99.49248895434464,
        "AGILITY": 92.86892488954346,
        "INTELLECT": 105.08689248895436,
        "WILL": 143.86303387334314,
        "BASE_HP": 5214,
        "BASE_ATTACK": 296,
        "BASE_DEFENSE": 0,
        "WEIGHT": 1,
        "CRITICAL_RATE": 0.05,
        "ATTACK_RANGE": 3
      }
    },
    {
      "level": 86,
      "operatorPromotionStage": 4,
      "attributes": {
        "STRENGTH": 100.52167052387966,
        "AGILITY": 93.87018725015781,
        "INTELLECT": 106.16978750262993,
        "WILL": 145.39711760993058,
        "BASE_HP": 5270,
        "BASE_ATTACK": 299,
        "BASE_DEFENSE": 0,
        "WEIGHT": 1,
        "CRITICAL_RATE": 0.05,
        "ATTACK_RANGE": 3
      }
    },
    {
      "level": 87,
      "operatorPromotionStage": 4,
      "attributes": {
        "STRENGTH": 101.55085209341469,
        "AGILITY": 94.87144961077216,
        "INTELLECT": 107.25268251630551,
        "WILL": 146.93120134651798,
        "BASE_HP": 5327,
        "BASE_ATTACK": 302,
        "BASE_DEFENSE": 0,
        "WEIGHT": 1,
        "CRITICAL_RATE": 0.05,
        "ATTACK_RANGE": 3
      }
    },
    {
      "level": 88,
      "operatorPromotionStage": 4,
      "attributes": {
        "STRENGTH": 102.58003366294972,
        "AGILITY": 95.87271197138651,
        "INTELLECT": 108.33557752998108,
        "WILL": 148.4652850831054,
        "BASE_HP": 5383,
        "BASE_ATTACK": 305,
        "BASE_DEFENSE": 0,
        "WEIGHT": 1,
        "CRITICAL_RATE": 0.05,
        "ATTACK_RANGE": 3
      }
    },
    {
      "level": 89,
      "operatorPromotionStage": 4,
      "attributes": {
        "STRENGTH": 103.60921523248476,
        "AGILITY": 96.87397433200086,
        "INTELLECT": 109.41847254365665,
        "WILL": 149.99936881969282,
        "BASE_HP": 5439,
        "BASE_ATTACK": 309,
        "BASE_DEFENSE": 0,
        "WEIGHT": 1,
        "CRITICAL_RATE": 0.05,
        "ATTACK_RANGE": 3
      }
    },
    {
      "level": 90,
      "operatorPromotionStage": 4,
      "attributes": {
        "STRENGTH": 104.63839680201978,
        "AGILITY": 97.8752366926152,
        "INTELLECT": 110.50136755733223,
        "WILL": 151.53345255628025,
        "BASE_HP": 5495,
        "BASE_ATTACK": 312,
        "BASE_DEFENSE": 0,
        "WEIGHT": 1,
        "CRITICAL_RATE": 0.05,
        "ATTACK_RANGE": 3
      }
    },
    {
      "level": 91,
      "operatorPromotionStage": 4,
      "attributes": {
        "STRENGTH": 105.66757837155481,
        "AGILITY": 98.87649905322955,
        "INTELLECT": 111.5842625710078,
        "WILL": 153.06753629286766,
        "BASE_HP": 5551,
        "BASE_ATTACK": 315,
        "BASE_DEFENSE": 0,
        "WEIGHT": 1,
        "CRITICAL_RATE": 0.05,
        "ATTACK_RANGE": 3
      }
    },
    {
      "level": 92,
      "operatorPromotionStage": 4,
      "attributes": {
        "STRENGTH": 106.69675994108985,
        "AGILITY": 99.8777614138439,
        "INTELLECT": 112.66715758468338,
        "WILL": 154.6016200294551,
        "BASE_HP": 5607,
        "BASE_ATTACK": 318,
        "BASE_DEFENSE": 0,
        "WEIGHT": 1,
        "CRITICAL_RATE": 0.05,
        "ATTACK_RANGE": 3
      }
    },
    {
      "level": 93,
      "operatorPromotionStage": 4,
      "attributes": {
        "STRENGTH": 107.72594151062488,
        "AGILITY": 100.87902377445825,
        "INTELLECT": 113.75005259835895,
        "WILL": 156.1357037660425,
        "BASE_HP": 5663,
        "BASE_ATTACK": 321,
        "BASE_DEFENSE": 0,
        "WEIGHT": 1,
        "CRITICAL_RATE": 0.05,
        "ATTACK_RANGE": 3
      }
    },
    {
      "level": 94,
      "operatorPromotionStage": 4,
      "attributes": {
        "STRENGTH": 108.7551230801599,
        "AGILITY": 101.8802861350726,
        "INTELLECT": 114.83294761203452,
        "WILL": 157.66978750262993,
        "BASE_HP": 5719,
        "BASE_ATTACK": 324,
        "BASE_DEFENSE": 0,
        "WEIGHT": 1,
        "CRITICAL_RATE": 0.05,
        "ATTACK_RANGE": 3
      }
    },
    {
      "level": 95,
      "operatorPromotionStage": 4,
      "attributes": {
        "STRENGTH": 109.78430464969493,
        "AGILITY": 102.88154849568694,
        "INTELLECT": 115.9158426257101,
        "WILL": 159.20387123921734,
        "BASE_HP": 5776,
        "BASE_ATTACK": 328,
        "BASE_DEFENSE": 0,
        "WEIGHT": 1,
        "CRITICAL_RATE": 0.05,
        "ATTACK_RANGE": 3
      }
    },
    {
      "level": 96,
      "operatorPromotionStage": 4,
      "attributes": {
        "STRENGTH": 110.81348621922997,
        "AGILITY": 103.88281085630129,
        "INTELLECT": 116.99873763938567,
        "WILL": 160.73795497580477,
        "BASE_HP": 5832,
        "BASE_ATTACK": 331,
        "BASE_DEFENSE": 0,
        "WEIGHT": 1,
        "CRITICAL_RATE": 0.05,
        "ATTACK_RANGE": 3
      }
    },
    {
      "level": 97,
      "operatorPromotionStage": 4,
      "attributes": {
        "STRENGTH": 111.842667788765,
        "AGILITY": 104.88407321691565,
        "INTELLECT": 118.08163265306125,
        "WILL": 162.27203871239217,
        "BASE_HP": 5888,
        "BASE_ATTACK": 334,
        "BASE_DEFENSE": 0,
        "WEIGHT": 1,
        "CRITICAL_RATE": 0.05,
        "ATTACK_RANGE": 3
      }
    },
    {
      "level": 98,
      "operatorPromotionStage": 4,
      "attributes": {
        "STRENGTH": 112.87184935830003,
        "AGILITY": 105.88533557753,
        "INTELLECT": 119.16452766673682,
        "WILL": 163.80612244897958,
        "BASE_HP": 5944,
        "BASE_ATTACK": 337,
        "BASE_DEFENSE": 0,
        "WEIGHT": 1,
        "CRITICAL_RATE": 0.05,
        "ATTACK_RANGE": 3
      }
    },
    {
      "level": 99,
      "operatorPromotionStage": 4,
      "attributes": {
        "STRENGTH": 113.90103092783507,
        "AGILITY": 106.88659793814435,
        "INTELLECT": 120.24742268041238,
        "WILL": 165.340206185567,
        "BASE_HP": 6000,
        "BASE_ATTACK": 340,
        "BASE_DEFENSE": 0,
        "WEIGHT": 1,
        "CRITICAL_RATE": 0.05,
        "ATTACK_RANGE": 3
      }
    }
  ],
  "skills": {
    "BASIC_ATTACK": {
      "name": "Audio Noise",
      "description": "BASIC ATTACK: \nAn attack with up to 4 sequences that deals Physical DMG. As the controlled operator, Final Strike also deals  Stagger. \n\nDIVE ATTACK: \nBasic attack performed in mid-air becomes a dive attack that deals Physical DMG to nearby enemies. \n\nFINISHER: \nBasic attack performed near a Staggered enemy becomes a finisher that deals massive Physical DMG and recovers some SP.",
      "segments": [
        {
          "eventComponentType": "SEGMENT",
          "duration": {
            "value": 0.467,
            "unit": "SECOND"
          },
          "frames": [
            {
              "eventComponentType": "FRAME",
              "offset": {
                "value": 0.2,
                "unit": "SECOND"
              },
              "dataSources": [
                "END_AXIS"
              ],
              "multipliers": [
                {
                  "level": 1,
                  "atk_scale": 0.25,
                  "atb": 0
                },
                {
                  "level": 2,
                  "atk_scale": 0.28,
                  "atb": 0
                },
                {
                  "level": 3,
                  "atk_scale": 0.3,
                  "atb": 0
                },
                {
                  "level": 4,
                  "atk_scale": 0.33,
                  "atb": 0
                },
                {
                  "level": 5,
                  "atk_scale": 0.35,
                  "atb": 0
                },
                {
                  "level": 6,
                  "atk_scale": 0.38,
                  "atb": 0
                },
                {
                  "level": 7,
                  "atk_scale": 0.4,
                  "atb": 0
                },
                {
                  "level": 8,
                  "atk_scale": 0.43,
                  "atb": 0
                },
                {
                  "level": 9,
                  "atk_scale": 0.45,
                  "atb": 0
                },
                {
                  "level": 10,
                  "atk_scale": 0.48,
                  "atb": 0
                },
                {
                  "level": 11,
                  "atk_scale": 0.52,
                  "atb": 0
                },
                {
                  "level": 12,
                  "atk_scale": 0.56,
                  "atb": 0
                }
              ]
            }
          ],
          "dataSources": [
            "END_AXIS"
          ]
        },
        {
          "eventComponentType": "SEGMENT",
          "duration": {
            "value": 0.567,
            "unit": "SECOND"
          },
          "frames": [
            {
              "eventComponentType": "FRAME",
              "offset": {
                "value": 0.2,
                "unit": "SECOND"
              },
              "dataSources": [
                "END_AXIS"
              ],
              "multipliers": [
                {
                  "level": 1,
                  "atk_scale": 0.3,
                  "atb": 0
                },
                {
                  "level": 2,
                  "atk_scale": 0.33,
                  "atb": 0
                },
                {
                  "level": 3,
                  "atk_scale": 0.36,
                  "atb": 0
                },
                {
                  "level": 4,
                  "atk_scale": 0.39,
                  "atb": 0
                },
                {
                  "level": 5,
                  "atk_scale": 0.42,
                  "atb": 0
                },
                {
                  "level": 6,
                  "atk_scale": 0.45,
                  "atb": 0
                },
                {
                  "level": 7,
                  "atk_scale": 0.48,
                  "atb": 0
                },
                {
                  "level": 8,
                  "atk_scale": 0.51,
                  "atb": 0
                },
                {
                  "level": 9,
                  "atk_scale": 0.54,
                  "atb": 0
                },
                {
                  "level": 10,
                  "atk_scale": 0.58,
                  "atb": 0
                },
                {
                  "level": 11,
                  "atk_scale": 0.62,
                  "atb": 0
                },
                {
                  "level": 12,
                  "atk_scale": 0.68,
                  "atb": 0
                }
              ]
            }
          ],
          "dataSources": [
            "END_AXIS"
          ]
        },
        {
          "eventComponentType": "SEGMENT",
          "duration": {
            "value": 0.967,
            "unit": "SECOND"
          },
          "frames": [
            {
              "eventComponentType": "FRAME",
              "offset": {
                "value": 0.23,
                "unit": "SECOND"
              },
              "dataSources": [
                "END_AXIS"
              ],
              "multipliers": [
                {
                  "level": 1,
                  "atk_scale": 0.15,
                  "atb": 0
                },
                {
                  "level": 2,
                  "atk_scale": 0.17,
                  "atb": 0
                },
                {
                  "level": 3,
                  "atk_scale": 0.18,
                  "atb": 0
                },
                {
                  "level": 4,
                  "atk_scale": 0.2,
                  "atb": 0
                },
                {
                  "level": 5,
                  "atk_scale": 0.21,
                  "atb": 0
                },
                {
                  "level": 6,
                  "atk_scale": 0.23,
                  "atb": 0
                },
                {
                  "level": 7,
                  "atk_scale": 0.24,
                  "atb": 0
                },
                {
                  "level": 8,
                  "atk_scale": 0.26,
                  "atb": 0
                },
                {
                  "level": 9,
                  "atk_scale": 0.27,
                  "atb": 0
                },
                {
                  "level": 10,
                  "atk_scale": 0.29,
                  "atb": 0
                },
                {
                  "level": 11,
                  "atk_scale": 0.31,
                  "atb": 0
                },
                {
                  "level": 12,
                  "atk_scale": 0.34,
                  "atb": 0
                }
              ]
            },
            {
              "eventComponentType": "FRAME",
              "offset": {
                "value": 0.6,
                "unit": "SECOND"
              },
              "dataSources": [
                "END_AXIS"
              ],
              "multipliers": [
                {
                  "level": 1,
                  "atk_scale": 0.2
                },
                {
                  "level": 2,
                  "atk_scale": 0.22
                },
                {
                  "level": 3,
                  "atk_scale": 0.24
                },
                {
                  "level": 4,
                  "atk_scale": 0.26
                },
                {
                  "level": 5,
                  "atk_scale": 0.28
                },
                {
                  "level": 6,
                  "atk_scale": 0.3
                },
                {
                  "level": 7,
                  "atk_scale": 0.32
                },
                {
                  "level": 8,
                  "atk_scale": 0.34
                },
                {
                  "level": 9,
                  "atk_scale": 0.36
                },
                {
                  "level": 10,
                  "atk_scale": 0.39
                },
                {
                  "level": 11,
                  "atk_scale": 0.42
                },
                {
                  "level": 12,
                  "atk_scale": 0.45
                }
              ]
            }
          ],
          "dataSources": [
            "END_AXIS"
          ]
        },
        {
          "eventComponentType": "SEGMENT",
          "duration": {
            "value": 1.567,
            "unit": "SECOND"
          },
          "frames": [
            {
              "eventComponentType": "FRAME",
              "offset": {
                "value": 0.7,
                "unit": "SECOND"
              },
              "effects": [
                {
                  "verbType": "RECOVER",
                  "objectType": "SKILL_POINT",
                  "cardinality": 19,
                  "prepositionType": "TO",
                  "toObjectType": "THIS_OPERATOR"
                },
                {
                  "verbType": "RECOVER",
                  "objectType": "STAGGER",
                  "cardinality": 17,
                  "prepositionType": "TO",
                  "toObjectType": "THIS_OPERATOR"
                }
              ],
              "dataSources": [
                "END_AXIS"
              ],
              "multipliers": [
                {
                  "level": 1,
                  "atk_scale": 0.4,
                  "poise": 17,
                  "atb": 19
                },
                {
                  "level": 2,
                  "atk_scale": 0.44,
                  "poise": 17,
                  "atb": 19
                },
                {
                  "level": 3,
                  "atk_scale": 0.48,
                  "poise": 17,
                  "atb": 19
                },
                {
                  "level": 4,
                  "atk_scale": 0.52,
                  "poise": 17,
                  "atb": 19
                },
                {
                  "level": 5,
                  "atk_scale": 0.56,
                  "poise": 17,
                  "atb": 19
                },
                {
                  "level": 6,
                  "atk_scale": 0.6,
                  "poise": 17,
                  "atb": 19
                },
                {
                  "level": 7,
                  "atk_scale": 0.64,
                  "poise": 17,
                  "atb": 19
                },
                {
                  "level": 8,
                  "atk_scale": 0.68,
                  "poise": 17,
                  "atb": 19
                },
                {
                  "level": 9,
                  "atk_scale": 0.72,
                  "poise": 17,
                  "atb": 19
                },
                {
                  "level": 10,
                  "atk_scale": 0.77,
                  "poise": 17,
                  "atb": 19
                },
                {
                  "level": 11,
                  "atk_scale": 0.83,
                  "poise": 17,
                  "atb": 19
                },
                {
                  "level": 12,
                  "atk_scale": 0.9,
                  "poise": 17,
                  "atb": 19
                }
              ]
            }
          ],
          "dataSources": [
            "END_AXIS"
          ]
        },
        {
          "eventComponentType": "SEGMENT",
          "duration": {
            "value": 0,
            "unit": "SECOND"
          },
          "frames": [],
          "dataSources": [
            "END_AXIS"
          ]
        },
        {
          "eventComponentType": "SEGMENT",
          "name": "Finisher",
          "duration": {
            "value": 0,
            "unit": "SECOND"
          },
          "frames": [
            {
              "eventComponentType": "FRAME",
              "offset": {
                "value": 0,
                "unit": "SECOND"
              },
              "multipliers": [
                {
                  "level": 1,
                  "atk_scale": 4
                },
                {
                  "level": 2,
                  "atk_scale": 4.4
                },
                {
                  "level": 3,
                  "atk_scale": 4.8
                },
                {
                  "level": 4,
                  "atk_scale": 5.2
                },
                {
                  "level": 5,
                  "atk_scale": 5.6
                },
                {
                  "level": 6,
                  "atk_scale": 6
                },
                {
                  "level": 7,
                  "atk_scale": 6.4
                },
                {
                  "level": 8,
                  "atk_scale": 6.8
                },
                {
                  "level": 9,
                  "atk_scale": 7.2
                },
                {
                  "level": 10,
                  "atk_scale": 7.7
                },
                {
                  "level": 11,
                  "atk_scale": 8.3
                },
                {
                  "level": 12,
                  "atk_scale": 9
                }
              ]
            }
          ]
        },
        {
          "eventComponentType": "SEGMENT",
          "name": "Dive",
          "duration": {
            "value": 0,
            "unit": "SECOND"
          },
          "frames": [
            {
              "eventComponentType": "FRAME",
              "offset": {
                "value": 0,
                "unit": "SECOND"
              },
              "multipliers": [
                {
                  "level": 1,
                  "atk_scale": 0.8
                },
                {
                  "level": 2,
                  "atk_scale": 0.88
                },
                {
                  "level": 3,
                  "atk_scale": 0.96
                },
                {
                  "level": 4,
                  "atk_scale": 1.04
                },
                {
                  "level": 5,
                  "atk_scale": 1.12
                },
                {
                  "level": 6,
                  "atk_scale": 1.2
                },
                {
                  "level": 7,
                  "atk_scale": 1.28
                },
                {
                  "level": 8,
                  "atk_scale": 1.36
                },
                {
                  "level": 9,
                  "atk_scale": 1.44
                },
                {
                  "level": 10,
                  "atk_scale": 1.54
                },
                {
                  "level": 11,
                  "atk_scale": 1.66
                },
                {
                  "level": 12,
                  "atk_scale": 1.8
                }
              ]
            }
          ]
        },
        {
          "eventComponentType": "SEGMENT",
          "name": "Final",
          "duration": {
            "value": 0,
            "unit": "SECOND"
          },
          "frames": [
            {
              "eventComponentType": "FRAME",
              "offset": {
                "value": 0,
                "unit": "SECOND"
              },
              "multipliers": [
                {
                  "level": 1,
                  "atk_scale": 0.4
                },
                {
                  "level": 2,
                  "atk_scale": 0.44
                },
                {
                  "level": 3,
                  "atk_scale": 0.48
                },
                {
                  "level": 4,
                  "atk_scale": 0.52
                },
                {
                  "level": 5,
                  "atk_scale": 0.56
                },
                {
                  "level": 6,
                  "atk_scale": 0.6
                },
                {
                  "level": 7,
                  "atk_scale": 0.64
                },
                {
                  "level": 8,
                  "atk_scale": 0.68
                },
                {
                  "level": 9,
                  "atk_scale": 0.72
                },
                {
                  "level": 10,
                  "atk_scale": 0.77
                },
                {
                  "level": 11,
                  "atk_scale": 0.83
                },
                {
                  "level": 12,
                  "atk_scale": 0.9
                }
              ]
            }
          ]
        }
      ],
      "id": "AUDIO_NOISE"
    },
    "BATTLE_SKILL": {
      "name": "Onomatopoeia",
      "description": "A lance thrust that fires a stream of freezing sound waves that deal Cryo DMG and apply Cryo Infliction to all enemies along its straight path.",
      "duration": {
        "value": 1.5,
        "unit": "SECOND"
      },
      "effects": [
        {
          "verbType": "EXPEND",
          "objectType": "SKILL_POINT",
          "cardinality": 100,
          "prepositionType": "TO",
          "toObjectType": "THIS_OPERATOR"
        },
        {
          "verbType": "RECOVER",
          "objectType": "ULTIMATE_ENERGY",
          "cardinality": 6.5,
          "prepositionType": "TO",
          "toObjectType": "THIS_OPERATOR"
        },
        {
          "verbType": "RECOVER",
          "objectType": "ULTIMATE_ENERGY",
          "cardinality": 6.5,
          "prepositionType": "TO",
          "toObjectType": "ALL_OPERATORS"
        }
      ],
      "frames": [
        {
          "eventComponentType": "FRAME",
          "offset": {
            "value": 0.7,
            "unit": "SECOND"
          },
          "effects": [
            {
              "verbType": "RECOVER",
              "objectType": "STAGGER",
              "cardinality": 10,
              "prepositionType": "TO",
              "toObjectType": "THIS_OPERATOR"
            },
            {
              "verbType": "APPLY",
              "objectType": "INFLICTION",
              "element": "CRYO",
              "stacks": 1,
              "prepositionType": "TO",
              "toObjectType": "ENEMY"
            }
          ],
          "dataSources": [
            "END_AXIS"
          ],
          "multipliers": [
            {
              "level": 1,
              "atk_scale": 1.56,
              "poise": 10
            },
            {
              "level": 2,
              "atk_scale": 1.71,
              "poise": 10
            },
            {
              "level": 3,
              "atk_scale": 1.87,
              "poise": 10
            },
            {
              "level": 4,
              "atk_scale": 2.02,
              "poise": 10
            },
            {
              "level": 5,
              "atk_scale": 2.18,
              "poise": 10
            },
            {
              "level": 6,
              "atk_scale": 2.34,
              "poise": 10
            },
            {
              "level": 7,
              "atk_scale": 2.49,
              "poise": 10
            },
            {
              "level": 8,
              "atk_scale": 2.65,
              "poise": 10
            },
            {
              "level": 9,
              "atk_scale": 2.8,
              "poise": 10
            },
            {
              "level": 10,
              "atk_scale": 3,
              "poise": 10
            },
            {
              "level": 11,
              "atk_scale": 3.23,
              "poise": 10
            },
            {
              "level": 12,
              "atk_scale": 3.5,
              "poise": 10
            }
          ]
        }
      ],
      "id": "ONOMATOPOEIA"
    },
    "COMBO_SKILL": {
      "name": "Distortion",
      "description": "COMBO TRIGGER: When an enemy suffers Solidification. \nQuickly moves to the enemy's side to deal Physical DMG and forcibly Lift enemies in a small area. If the skill hits a target with Solidification, the skill deals additional DMG and applies Physical Susceptibility.",
      "duration": {
        "value": 0.67,
        "unit": "SECOND"
      },
      "effects": [
        {
          "verbType": "EXPEND",
          "objectType": "COOLDOWN",
          "cardinality": 15,
          "prepositionType": "TO",
          "toObjectType": "THIS_OPERATOR"
        },
        {
          "verbType": "RECOVER",
          "objectType": "ULTIMATE_ENERGY",
          "cardinality": 10,
          "prepositionType": "TO",
          "toObjectType": "THIS_OPERATOR"
        }
      ],
      "animation": {
        "duration": {
          "value": 0.5,
          "unit": "SECOND"
        },
        "timeInteractionType": "TIME_STOP"
      },
      "frames": [
        {
          "eventComponentType": "FRAME",
          "offset": {
            "value": 0.63,
            "unit": "SECOND"
          },
          "effects": [
            {
              "verbType": "RECOVER",
              "objectType": "STAGGER",
              "cardinality": 10,
              "prepositionType": "TO",
              "toObjectType": "THIS_OPERATOR"
            }
          ],
          "dataSources": [
            "END_AXIS"
          ],
          "multipliers": [
            {
              "level": 1,
              "atk_scale": 1.6,
              "atk_scale2": 2.8,
              "poise": 10,
              "usp": 10,
              "rate": 0.1,
              "duration": 6
            },
            {
              "level": 2,
              "atk_scale": 1.76,
              "atk_scale2": 3.08,
              "poise": 10,
              "usp": 10,
              "rate": 0.1,
              "duration": 6
            },
            {
              "level": 3,
              "atk_scale": 1.92,
              "atk_scale2": 3.36,
              "poise": 10,
              "usp": 10,
              "rate": 0.1,
              "duration": 6
            },
            {
              "level": 4,
              "atk_scale": 2.08,
              "atk_scale2": 3.64,
              "poise": 10,
              "usp": 10,
              "rate": 0.1,
              "duration": 6
            },
            {
              "level": 5,
              "atk_scale": 2.24,
              "atk_scale2": 3.92,
              "poise": 10,
              "usp": 10,
              "rate": 0.1,
              "duration": 6
            },
            {
              "level": 6,
              "atk_scale": 2.4,
              "atk_scale2": 4.2,
              "poise": 10,
              "usp": 10,
              "rate": 0.1,
              "duration": 6
            },
            {
              "level": 7,
              "atk_scale": 2.56,
              "atk_scale2": 4.48,
              "poise": 10,
              "usp": 10,
              "rate": 0.1,
              "duration": 6
            },
            {
              "level": 8,
              "atk_scale": 2.72,
              "atk_scale2": 4.76,
              "poise": 10,
              "usp": 10,
              "rate": 0.1,
              "duration": 6
            },
            {
              "level": 9,
              "atk_scale": 2.88,
              "atk_scale2": 5.04,
              "poise": 10,
              "usp": 10,
              "rate": 0.1,
              "duration": 6
            },
            {
              "level": 10,
              "atk_scale": 3.08,
              "atk_scale2": 5.39,
              "poise": 10,
              "usp": 10,
              "rate": 0.15,
              "duration": 6
            },
            {
              "level": 11,
              "atk_scale": 3.32,
              "atk_scale2": 5.81,
              "poise": 10,
              "usp": 10,
              "rate": 0.15,
              "duration": 6
            },
            {
              "level": 12,
              "atk_scale": 3.6,
              "atk_scale2": 6.3,
              "poise": 10,
              "usp": 10,
              "rate": 0.15,
              "duration": 6
            }
          ]
        }
      ],
      "id": "DISTORTION",
      "trigger": {
        "requires": [
          "SOLIDIFICATION"
        ],
        "description": "Enemy has Solidification"
      }
    },
    "ULTIMATE": {
      "name": "Tremolo",
      "description": "Estella expends all her strength to unleash a powerful slam of the spear shaft, dealing Physical DMG to all enemies in a circular area around self. To enemies with Physical Susceptibility, the skill forcibly applies Lift to them.",
      "duration": {
        "value": 2,
        "unit": "SECOND"
      },
      "effects": [
        {
          "verbType": "EXPEND",
          "objectType": "ULTIMATE_ENERGY",
          "cardinality": 63,
          "prepositionType": "TO",
          "toObjectType": "THIS_OPERATOR"
        }
      ],
      "animation": {
        "duration": {
          "value": 1.8,
          "unit": "SECOND"
        },
        "timeInteractionType": "TIME_STOP"
      },
      "frames": [
        {
          "eventComponentType": "FRAME",
          "offset": {
            "value": 1.8,
            "unit": "SECOND"
          },
          "dataSources": [
            "END_AXIS"
          ],
          "multipliers": [
            {
              "level": 1,
              "atk_scale": 4.89,
              "poise": 15
            },
            {
              "level": 2,
              "atk_scale": 5.38,
              "poise": 15
            },
            {
              "level": 3,
              "atk_scale": 5.86,
              "poise": 15
            },
            {
              "level": 4,
              "atk_scale": 6.35,
              "poise": 15
            },
            {
              "level": 5,
              "atk_scale": 6.84,
              "poise": 15
            },
            {
              "level": 6,
              "atk_scale": 7.33,
              "poise": 15
            },
            {
              "level": 7,
              "atk_scale": 7.82,
              "poise": 15
            },
            {
              "level": 8,
              "atk_scale": 8.31,
              "poise": 15
            },
            {
              "level": 9,
              "atk_scale": 8.8,
              "poise": 15
            },
            {
              "level": 10,
              "atk_scale": 9.41,
              "poise": 20
            },
            {
              "level": 11,
              "atk_scale": 10.14,
              "poise": 20
            },
            {
              "level": 12,
              "atk_scale": 11,
              "poise": 20
            }
          ]
        }
      ],
      "id": "TREMOLO"
    }
  },
  "talents": {
    "one": {
      "name": "Commiseration",
      "maxLevel": 2
    },
    "two": {
      "name": "Laziness Pays Off Now",
      "maxLevel": 2
    },
    "attributeIncrease": {
      "name": "Stalwart",
      "attribute": "WILL"
    }
  },
  "displayColor": "#6699cc",
  "basicAttackDefaultDuration": 0.15
}
