{
  "onTriggerClause": [
    {
      "conditions": [
        {
          "subject": "ENEMY",
          "verb": "IS",
          "object": "SOLIDIFIED"
        }
      ],
      "effects": [
        {
          "verb": "APPLY",
          "object": "STATUS",
          "objectId": "OBJ_RAZORHORN_CONQUEST_OF_ICY_PEAKS",
          "toDeterminer": "THIS",
          "to": "OPERATOR"
        }
      ]
    }
  ],
  "properties": {
    "id": "INFLICTION_CONQUEST_OF_ICY_PEAKS",
    "eventCategoryType": "WEAPON_STAT"
  },
  "metadata": {
    "originId": "OBJ_RAZORHORN",
    "dataSources": [
      "ENDFIELD_WIKI"
    ],
    "dataStatus": "RECONCILED"
  }
}
