{
  "clause": [
    {
      "conditions": [],
      "effects": [
        {
          "verb": "APPLY",
          "object": "STAT",
          "objectId": "CRITICAL_RATE",
          "toDeterminer": "THIS",
          "to": "OPERATOR",
          "with": {
            "value": {
              "verb": "VARY_BY",
              "object": "SKILL_LEVEL",
              "value": [
                0.15,
                0.15,
                0.15,
                0.17,
                0.17,
                0.17,
                0.19,
                0.19,
                0.21,
                0.21,
                0.23,
                0.25
              ],
              "of": {
                "object": "OPERATOR",
                "determiner": "THIS"
              }
            }
          }
        },
        {
          "verb": "APPLY",
          "object": "STAT",
          "objectId": "CRITICAL_DAMAGE",
          "toDeterminer": "THIS",
          "to": "OPERATOR",
          "with": {
            "value": {
              "verb": "VARY_BY",
              "object": "SKILL_LEVEL",
              "value": [
                0.3,
                0.3,
                0.3,
                0.34,
                0.34,
                0.34,
                0.38,
                0.38,
                0.42,
                0.42,
                0.46,
                0.5
              ],
              "of": {
                "object": "OPERATOR",
                "determiner": "THIS"
              }
            }
          }
        }
      ]
    }
  ],
  "properties": {
    "id": "BLAZING_SHADOW_CRIT",
    "name": "Blazing Shadow Crit",
    "to": "OPERATOR",
    "toDeterminer": "THIS",
    "duration": {
      "value": {
        "verb": "IS",
        "value": 15
      },
      "unit": "SECOND"
    },
    "stacks": {
      "limit": {
        "verb": "IS",
        "value": 1
      },
      "interactionType": "RESET"
    },
    "eventType": "STATUS",
    "eventCategoryType": "STATUS",
    "description": "Combo skill Moment of Blazing Shadow grants increased Critical Rate and Critical DMG Dealt."
  },
  "metadata": {
    "originId": "ROSSI",
    "dataSources": [
      "ENDFIELD_WIKI",
      "WARFARIN"
    ],
    "dataStatus": "VERIFIED"
  },
  "clauseType": "ALL"
}
