{
  "clause": [
    {
      "conditions": [],
      "effects": [
        {
          "verb": "APPLY",
          "object": "BASE_DEFENSE",
          "toDeterminer": "THIS",
          "to": "OPERATOR",
          "with": {
            "value": {
              "verb": "IS",
              "value": 10.8
            }
          }
        },
        {
          "verb": "APPLY",
          "object": "WILL",
          "toDeterminer": "THIS",
          "to": "OPERATOR",
          "with": {
            "value": {
              "verb": "VARY_BY",
              "object": "SKILL_LEVEL",
              "value": [
                22,
                22,
                22,
                22
              ],
              "ofDeterminer": "THIS",
              "of": "OPERATOR"
            }
          }
        },
        {
          "verb": "APPLY",
          "object": "HP_BONUS",
          "toDeterminer": "THIS",
          "to": "OPERATOR",
          "with": {
            "value": {
              "verb": "VARY_BY",
              "object": "SKILL_LEVEL",
              "value": [
                0.228,
                0.228,
                0.228,
                0.228
              ],
              "ofDeterminer": "THIS",
              "of": "OPERATOR"
            }
          }
        }
      ]
    }
  ],
  "properties": {
    "id": "MINER_COMM",
    "name": "Miner Comm",
    "type": "KIT",
    "gearSet": "NONE"
  }
}
