[
  {
    "clause": [
      {
        "conditions": [],
        "effects": [
          {
            "verb": "APPLY",
            "object": "ARTS_DAMAGE_BONUS",
            "with": {
              "value": {
                "verb": "VARY_BY",
                "object": "SKILL_LEVEL",
                "value": [
                  0.24,
                  0.288,
                  0.336,
                  0.384,
                  0.432,
                  0.48,
                  0.528,
                  0.576,
                  0.672
                ]
              }
            }
          }
        ]
      }
    ],
    "properties": {
      "id": "OBLIVION_HUMILIATION",
      "name": "Humiliation",
      "description": "Ultimate: 24-48%, Combo: 12-24%",
      "duration": {
        "value": {
          "verb": "IS",
          "value": 15
        },
        "unit": "SECOND"
      },
      "statusLevel": {
        "limit": {
          "verb": "IS",
          "value": 1
        },
        "interactionType": "RESET"
      },
      "to": "OPERATOR",
      "toDeterminer": "THIS"
    },
    "metadata": {
      "originId": "OBLIVION",
      "dataSources": [
        "ENDFIELD_WIKI"
      ]
    }
  }
]
