{
  "weaponName": "Finchaser 3.0",
  "statusEvents": [
    {
      "clause": [
        {
          "conditions": [],
          "effects": [
            {
              "verb": "APPLY",
              "object": "CRYO_DAMAGE_BONUS",
              "to": "ENEMY",
              "with": {
                "value": {
                  "verb": "IS",
                  "valueMin": 0.07,
                  "valueMax": 0.14
                }
              }
            }
          ]
        }
      ],
      "properties": {
        "type": "WEAPON_EFFECT",
        "id": "FINCHASER_3_0_FIN_CHASERS_INTENT",
        "name": "Fin Chaser's Intent",
        "duration": {
          "value": [
            15
          ],
          "unit": "SECOND"
        },
        "stacks": {
          "limit": {
            "verb": "IS",
            "value": 1
          },
          "interactionType": "RESET"
        }
      },
      "metadata": {
        "originId": "FINCHASER_3_0",
        "description": "Fin Chaser's Intent",
        "note": "Enemy Cryo DMG Taken (Fragility)"
      },
      "onTriggerClause": [
        {
          "conditions": [
            {
              "subject": "ENEMY",
              "verb": "IS",
              "object": "SOLIDIFIED"
            }
          ]
        }
      ]
    }
  ]
}
