{
  "properties": {
    "id": "WULFGARD_NATURAL_PREDATOR",
    "name": "Natural Predator",
    "target": "OPERATOR",
    "targetDeterminer": "THIS",
    "stacks": {
      "limit": {
        "verb": "IS",
        "value": 1
      },
      "interactionType": "NONE"
    },
    "duration": {
      "value": {
        "verb": "IS",
        "value": -1
      },
      "unit": "SECOND"
    },
    "minPotential": 5,
    "eventType": "STATUS",
    "eventCategoryType": "SKILL_STATUS",
    "description": "Casting the ultimate Wolven Fury immediately resets the cooldown of the combo skill Frag Grenade·β."
  },
  "metadata": {
    "originId": "NATURAL_PREDATOR"
  },
  "onTriggerClause": [
    {
      "conditions": [
        {
          "subjectDeterminer": "THIS",
          "subject": "OPERATOR",
          "verb": "PERFORM",
          "object": "ULTIMATE"
        }
      ]
    }
  ],
  "clause": [
    {
      "conditions": [],
      "effects": [
        {
          "verb": "RESET",
          "object": "COOLDOWN",
          "objectId": "COMBO_SKILL"
        }
      ]
    }
  ],
  "clauseType": "ALL"
}
